swanshare/__init__.py
swanshare/_version.py
swanshare/serverextension.py
swanshare/nbextension/extension.js
swanshare-2.0.3.data/data/etc/jupyter/jupyter_server_config.d/swanshare.json
swanshare-2.0.3.dist-info/METADATA
swanshare-2.0.3.dist-info/WHEEL
swanshare-2.0.3.dist-info/top_level.txt
swanshare-2.0.3.dist-info/RECORD
